convexAdam/__init__.py
convexAdam/apply_convex.py
convexAdam/convex_adam_MIND.py
convexAdam/convex_adam_nnUNet.py
convexAdam/convex_adam_translation.py
convexAdam/convex_adam_utils.py
convexadam-0.2.0.dist-info/LICENSE
convexadam-0.2.0.dist-info/METADATA
convexadam-0.2.0.dist-info/WHEEL
convexadam-0.2.0.dist-info/top_level.txt
convexadam-0.2.0.dist-info/RECORD
