Metadata-Version: 2.2
Name: convexAdam
Version: 0.2.0
Summary: Convex Adam
Home-page: https://github.com/multimodallearning/convexAdam
Author: Mattias Paul Heinrich
Author-email: heinrich@imi.uni-luebeck.de
License: Apache 2.0
Project-URL: Bug Tracker, https://github.com/multimodallearning/convexAdam/issues
Platform: unix
Platform: linux
Platform: osx
Platform: cygwin
Platform: win32
Classifier: Programming Language :: Python :: 3
Classifier: Programming Language :: Python :: 3 :: Only
Classifier: Programming Language :: Python :: 3.6
Classifier: Programming Language :: Python :: 3.7
Classifier: Programming Language :: Python :: 3.8
Classifier: Programming Language :: Python :: 3.9
Classifier: Programming Language :: Python :: 3.10
Classifier: Programming Language :: Python :: 3.11
Requires-Python: >=3.6
License-File: LICENSE
Requires-Dist: nibabel
Requires-Dist: numpy
Requires-Dist: scikit-learn
Requires-Dist: SimpleITK
Requires-Dist: torch
Provides-Extra: testing
Requires-Dist: pytest>=6.0; extra == "testing"
Requires-Dist: pytest-cov>=2.0; extra == "testing"
Requires-Dist: mypy>=0.910; extra == "testing"
Requires-Dist: flake8>=3.9; extra == "testing"
Requires-Dist: tox>=3.24; extra == "testing"
Dynamic: author-email
Dynamic: description
Dynamic: description-content-type
Dynamic: home-page
Dynamic: license
Dynamic: project-url
